3dstrudel/__init__.py
3dstrudel/configure.py
3dstrudel/nomenclature.py
3dstrudel/average/__init__.py
3dstrudel/average/mapAveraging.py
3dstrudel/average/superimpose_chimerax.py
3dstrudel/bin/__init__.py
3dstrudel/bin/strudel_chopModelMapMPI.py
3dstrudel/bin/strudel_mapAveraging.py
3dstrudel/bin/strudel_mapMotifValidation.py
3dstrudel/bin/strudel_penultimateClassifier.py
3dstrudel/bin/strudel_setChimeraX.py
3dstrudel/chop/__init__.py
3dstrudel/chop/chopMap.py
3dstrudel/chop/chopModelMapMPI.py
3dstrudel/chop/segmentResidueDensity.py
3dstrudel/classify/__init__.py
3dstrudel/classify/alignPrincipalAxes.py
3dstrudel/classify/penultimateClassifier.py
3dstrudel/classify/rotamerClassifier.py
3dstrudel/classify/inp/__init__.py
3dstrudel/lib/__init__.py
3dstrudel/lib/strudel/__init__.py
3dstrudel/lib/strudel/penultimate_rotamer_lib.py
3dstrudel/parse/__init__.py
3dstrudel/parse/mapParser.py
3dstrudel/sequence_finder/__init__.py
3dstrudel/sequence_finder/plot_results.py
3dstrudel/sequence_finder/run_seq_find_buc.py
3dstrudel/sequence_finder/run_seq_find_buc1.py
3dstrudel/sequence_finder/run_seq_find_buc_2.py
3dstrudel/sequence_finder/score_chimerax.py
3dstrudel/sequence_finder/sequenceFinder.py
3dstrudel/sequence_finder/structure_align.py
3dstrudel/sequence_finder/updated_score_chimerax.py
3dstrudel/utils/__init__.py
3dstrudel/utils/bioUtils.py
3dstrudel/utils/functions.py
3dstrudel/utils/modelMapUtils.py
3dstrudel/utils/nomenclature.py
3dstrudel/validation/__init__.py
3dstrudel/validation/bundleValidatioResults.py
3dstrudel/validation/mapMotifValidation.py
3dstrudel/validation/score_chimerax.py
3dstrudel-0.1.1.data/scripts/run_chopModelMapMPI.py
3dstrudel-0.1.1.data/scripts/run_mapAveraging.py
3dstrudel-0.1.1.data/scripts/run_mapMotifValidation.py
3dstrudel-0.1.1.data/scripts/run_penultimateClassifier.py
3dstrudel-0.1.1.data/scripts/strudel_chopModelMapMPI.py
3dstrudel-0.1.1.data/scripts/strudel_mapAveraging.py
3dstrudel-0.1.1.data/scripts/strudel_mapMotifValidation.py
3dstrudel-0.1.1.dist-info/METADATA
3dstrudel-0.1.1.dist-info/WHEEL
3dstrudel-0.1.1.dist-info/top_level.txt
3dstrudel-0.1.1.dist-info/RECORD
